darken/__init__.py
darken-0.0.4.dist-info/entry_points.txt
darken-0.0.4.dist-info/LICENSE
darken-0.0.4.dist-info/WHEEL
darken-0.0.4.dist-info/METADATA
darken-0.0.4.dist-info/RECORD
