Metadata-Version: 2.1
Name: darken
Version: 0.0.4
Summary: Deprecated, see darker that have a saner approach.
Home-page: https://github.com/Carreau/darken
License: UNKNOWN
Author: Matthias Bussonnier
Author-email: bussonniermatthias@gmail.com
Classifier: License :: OSI Approved :: MIT License
